doteki/__init__.py
doteki/cli.py
doteki/plugins/__init__.py
doteki/plugins/current_date.py
doteki/plugins/feed.py
doteki/plugins/figlet.py
doteki/plugins/lastfm.py
doteki/plugins/random_choice.py
doteki-0.0.8.dist-info/COPYING
doteki-0.0.8.dist-info/METADATA
doteki-0.0.8.dist-info/WHEEL
doteki-0.0.8.dist-info/entry_points.txt
doteki-0.0.8.dist-info/RECORD
