Metadata-Version: 2.1
Name: doteki
Version: 0.0.8
Summary: Easily add dynamic content to your GitHub profile
Home-page: https://doteki.org/
License: GPL-3.0-or-later
Author: Óscar Fernández
Author-email: osc@osc.garden
Requires-Python: >=3.11,<4.0
Classifier: Intended Audience :: Developers
Classifier: License :: OSI Approved :: GNU General Public License v3 or later (GPLv3+)
Classifier: Operating System :: OS Independent
Classifier: Programming Language :: Python :: 3
Classifier: Programming Language :: Python :: 3.11
Classifier: Programming Language :: Python :: 3.12
Provides-Extra: all
Provides-Extra: feed
Provides-Extra: figlet
Provides-Extra: lastfm
Requires-Dist: feedparser (>=6.0,<7.0) ; extra == "all" or extra == "feed"
Requires-Dist: pyfiglet (>=1.0.2,<2.0.0) ; extra == "all" or extra == "figlet"
Requires-Dist: requests (>=2.28,<3.0) ; extra == "all" or extra == "lastfm" or extra == "feed"
Project-URL: Documentation, https://doteki.org/docs/
Project-URL: Repository, https://github.com/welpo/doteki
